faiss_vector_aggregator/__init__.py
faiss_vector_aggregator/aggregator.py
faiss_vector_aggregator/embedding_methods.py
faiss_vector_aggregator/faiss_index_helpers.py
faiss_vector_aggregator/test.py
faiss_vector_aggregator/utils.py
faiss_vector_aggregator-0.3.0.dist-info/LICENSE
faiss_vector_aggregator-0.3.0.dist-info/METADATA
faiss_vector_aggregator-0.3.0.dist-info/WHEEL
faiss_vector_aggregator-0.3.0.dist-info/top_level.txt
faiss_vector_aggregator-0.3.0.dist-info/RECORD
