Metadata-Version: 2.1
Name: faiss-vector-aggregator
Version: 0.3.0
Summary: A package to aggregate embeddings in a Faiss vector store based on metadata columns.
Home-page: https://github.com/vinerya/faiss_vector_aggregator
Author: Moudather Chelbi
Author-email: moudather.chelbi@gmail.com
License: MIT
Platform: UNKNOWN
Classifier: Programming Language :: Python :: 3
Classifier: License :: OSI Approved :: MIT License
Classifier: Operating System :: OS Independent
Requires-Python: >=3.8
License-File: LICENSE
Requires-Dist: faiss-cpu
Requires-Dist: numpy
Requires-Dist: pickle-mixin
Requires-Dist: scikit-learn
Requires-Dist: scipy
